[
  {
    "id": "1838637497951170645",
    "name": "李老师不是你老师",
    "accountId": "whyyoutouzhele",
    "sensitive": false,
    "createdDate": "2024-09-25 01:51:54",
    "content": "一位年轻人在国内一商场弹奏《愿荣光归香港》，声援那些目前被非法拘禁在特训学校中的青少年们。 https://t.co/92yDrElYZq",
    "images": "",
    "videos": "/tweet/video/whyyoutouzhele/2024/09/25/1838637497951170645_0.jpg,",
    "isReply": false,
    "isRetweet": false,
    "isSelfThread": false,
    "likes": 0,
    "replies": 0,
    "retweets": 0,
    "views": 0,
    "originVideos": ""
  },
  {
    "id": "1838724180545540175",
    "name": "李老师不是你老师",
    "accountId": "whyyoutouzhele",
    "sensitive": false,
    "createdDate": "2024-09-25 07:36:21",
    "content": "9月24日，据华尔街日报报道，中国社科院经济研究所原副所长朱恒鹏受到调查，已被拘留并免职，据传他在一个私人聊天群中批评了习近平对国内经济的管理。 https://t.co/CrhfA5sI72",
    "images": "/tweet/image/whyyoutouzhele/2024/09/25/1838724180545540175_0.jpg,/tweet/image/whyyoutouzhele/2024/09/25/1838724180545540175_1.jpg,/tweet/image/whyyoutouzhele/2024/09/25/1838724180545540175_2.jpg,",
    "videos": "",
    "isReply": false,
    "isRetweet": false,
    "isSelfThread": false,
    "likes": 2772,
    "replies": 377,
    "retweets": 413,
    "views": 814432,
    "originVideos": ""
  },
  {
    "id": "1838721458236797086",
    "name": "李老师不是你老师",
    "accountId": "whyyoutouzhele",
    "sensitive": false,
    "createdDate": "2024-09-25 07:25:32",
    "content": "9月24日，中国商务部表示正在调查服装品牌Calvin Klein 和 Tommy Hilfiger 的所有者PVH 公司。此次调查将决定 PVH 是否因涉嫌抵制新疆棉制品而被列入“不可靠实体名单”。被列入黑名单将禁止该公司向中国销售产品或从中国采购产品。 https://t.co/396qnXSlrc",
    "images": "/tweet/image/whyyoutouzhele/2024/09/25/1838721458236797086_0.jpg,/tweet/image/whyyoutouzhele/2024/09/25/1838721458236797086_1.jpg,",
    "videos": "",
    "isReply": false,
    "isRetweet": false,
    "isSelfThread": false,
    "likes": 635,
    "replies": 149,
    "retweets": 77,
    "views": 282925,
    "originVideos": ""
  },
  {
    "id": "1838714605964570857",
    "name": "李老师不是你老师",
    "accountId": "whyyoutouzhele",
    "sensitive": false,
    "createdDate": "2024-09-25 06:58:18",
    "content": "https://t.co/p7xM8rjFR2",
    "images": "/tweet/image/whyyoutouzhele/2024/09/25/1838714605964570857_0.jpg,/tweet/image/whyyoutouzhele/2024/09/25/1838714605964570857_1.jpg,",
    "videos": "",
    "isReply": true,
    "isRetweet": false,
    "isSelfThread": false,
    "likes": 235,
    "replies": 37,
    "retweets": 5,
    "views": 174565,
    "originVideos": ""
  },
  {
    "id": "1838714310521942179",
    "name": "李老师不是你老师",
    "accountId": "whyyoutouzhele",
    "sensitive": false,
    "createdDate": "2024-09-25 06:57:07",
    "content": "9月24日，山东德州，因为家长和老师不满德州市第一中学（东校区）独立为德州市新城中学，在学校外抗议。 https://t.co/GtrQa0zrb7",
    "images": "",
    "videos": "/tweet/video/whyyoutouzhele/2024/09/25/1838714310521942179_0.jpg,/tweet/video/whyyoutouzhele/2024/09/25/1838714310521942179_1.jpg,/tweet/video/whyyoutouzhele/2024/09/25/1838714310521942179_2.jpg,/tweet/video/whyyoutouzhele/2024/09/25/1838714310521942179_3.jpg,",
    "isReply": false,
    "isRetweet": false,
    "isSelfThread": false,
    "likes": 457,
    "replies": 105,
    "retweets": 33,
    "views": 237178,
    "originVideos": "https://video.twimg.com/ext_tw_video/1838714017801469952/pu/vid/avc1/720x1280/0KN_WpvE9mIJJLXu.mp4?tag=12,https://video.twimg.com/ext_tw_video/1838714017805697024/pu/vid/avc1/720x1280/SoVBEBVpErJ6hpHU.mp4?tag=12,https://video.twimg.com/ext_tw_video/1838714017797308416/pu/vid/avc1/720x1280/kOeXsxltvU4smuJ-.mp4?tag=12,https://video.twimg.com/ext_tw_video/1838714017801555968/pu/vid/avc1/592x1124/k2BIuUE3B6IqpL3J.mp4?tag=12,"
  },
  {
    "id": "1838711766445937128",
    "name": "李老师不是你老师",
    "accountId": "whyyoutouzhele",
    "sensitive": false,
    "createdDate": "2024-09-25 06:47:01",
    "content": "9月23日晚，江苏南京。马路上突然出现大量百元大钞，路过的车主纷纷停下，迅速加入到捡拾钞票的队伍中。 https://t.co/8M4KvxvPHg",
    "images": "",
    "videos": "/tweet/video/whyyoutouzhele/2024/09/25/1838711766445937128_0.jpg,",
    "isReply": false,
    "isRetweet": false,
    "isSelfThread": false,
    "likes": 933,
    "replies": 170,
    "retweets": 92,
    "views": 546461,
    "originVideos": "https://video.twimg.com/ext_tw_video/1838711725639557120/pu/vid/avc1/720x1272/QTnJINwETvnIbCi3.mp4?tag=12,"
  },
  {
    "id": "1838708073545806249",
    "name": "李老师不是你老师",
    "accountId": "whyyoutouzhele",
    "sensitive": false,
    "createdDate": "2024-09-25 06:32:20",
    "content": "9月24日，广西南宁秀厢大道。一组疑似化粪池管线炸裂画面在网络热传。根据多个视角视频画面显示，一团黄色烟雾从路面喷出，随后有落在行驶中的车窗上，瞬间视线被遮挡，爆炸点有挖掘机器正在作业，旁边设有围挡。南宁应急管理局工作人员回应称，是排污管道爆裂，正在抢修，没有车辆受损和人员受伤。 https://t.co/sEl4Q7LzQj",
    "images": "",
    "videos": "/tweet/video/whyyoutouzhele/2024/09/25/1838708073545806249_0.jpg,/tweet/video/whyyoutouzhele/2024/09/25/1838708073545806249_1.jpg,/tweet/video/whyyoutouzhele/2024/09/25/1838708073545806249_2.jpg,",
    "isReply": false,
    "isRetweet": false,
    "isSelfThread": false,
    "likes": 652,
    "replies": 161,
    "retweets": 71,
    "views": 279419,
    "originVideos": "https://video.twimg.com/ext_tw_video/1838707753365188608/pu/vid/avc1/480x848/KVSsEzV8nHXiTgO5.mp4?tag=12,https://video.twimg.com/ext_tw_video/1838707753440657408/pu/vid/avc1/1280x720/PaJaEh_2mVoItods.mp4?tag=12,https://video.twimg.com/ext_tw_video/1838707753818148864/pu/vid/avc1/1280x718/zYeHnUJ1CLO0qu1q.mp4?tag=12,"
  },
  {
    "id": "1838707434019287163",
    "name": "李老师不是你老师",
    "accountId": "whyyoutouzhele",
    "sensitive": false,
    "createdDate": "2024-09-25 06:29:48",
    "content": "“订奶事件”再现：“学生入校被禁止自行携带牛奶，却允许喝学校提供的奶，这是什么道理？” 据报道，9月23日，有网友发视频称对山东德州一所学校的做法“难以理解”，引发关注。 \n\n相关视频显示，该校门口，学生正排队接受校方工作人员检查书包，合格才能进校。视频显示，有家长询问为什么不让孩子们自己带奶。对此，一名校方工作人员称因为天凉了。家长又问：学校奶为什么能喝？对方回答说，学校加热了。记者联系涉事的禹城市龙泽实验学校，其多个电话均无人接听。禹城市教体局工作人员则表示，已关注到此事，并已在核查处理中，后续会有正式通报。",
    "images": "",
    "videos": "/tweet/video/whyyoutouzhele/2024/09/25/1838707434019287163_0.jpg,",
    "isReply": false,
    "isRetweet": false,
    "isSelfThread": false,
    "likes": 936,
    "replies": 120,
    "retweets": 127,
    "views": 213746,
    "originVideos": "https://video.twimg.com/ext_tw_video/1838707395855306752/pu/vid/avc1/576x1024/PNxFI-jKxK79ViGt.mp4?tag=12,"
  },
  {
    "id": "1838706936382132535",
    "name": "李老师不是你老师",
    "accountId": "whyyoutouzhele",
    "sensitive": false,
    "createdDate": "2024-09-25 06:27:49",
    "content": "近日，江苏南京。“河海大学图书馆厕所发现摄像头”一事引发关注。9月23日，大河报记者向该校多部门了解相关情况。河海大学校保卫处工作人员称“不方便解答”；该校党政办公室一名老师表示，相关问题由学校宣传部负责。随后，记者向该校党委宣传部询问“此事报警了吗”，却被对方反问：“这个报警干什么？” https://t.co/Ph2BbHFupz",
    "images": "",
    "videos": "/tweet/video/whyyoutouzhele/2024/09/25/1838706936382132535_0.jpg,",
    "isReply": false,
    "isRetweet": false,
    "isSelfThread": false,
    "likes": 1067,
    "replies": 119,
    "retweets": 172,
    "views": 315446,
    "originVideos": "https://video.twimg.com/ext_tw_video/1838706849056456704/pu/vid/avc1/1280x720/7Yf3s5WuLsD5kdIp.mp4?tag=12,"
  },
  {
    "id": "1838706059923566754",
    "name": "李老师不是你老师",
    "accountId": "whyyoutouzhele",
    "sensitive": false,
    "createdDate": "2024-09-25 06:24:20",
    "content": "近日，有网友在某社交平台发帖表示，太原幼儿师范高等专科学校对2024年第二批事业编博士研究生引进录取情况进行公示，但该公示的最终结果却引起不少争议。\n从公示情况来看，拟引进的10名人才中大多为毕业于东南亚及东亚国家的博士研究生，如菲律宾亚当森大学、泰国易三仓大学、泰国西那瓦国际大学、菲律宾基督教大学以及韩国又石大学等，所学专业有汉语言文学、管理学、体育与运动、教育学、艺术学等。",
    "images": "/tweet/image/whyyoutouzhele/2024/09/25/1838706059923566754_0.jpg,",
    "videos": "",
    "isReply": false,
    "isRetweet": false,
    "isSelfThread": false,
    "likes": 610,
    "replies": 87,
    "retweets": 64,
    "views": 482098,
    "originVideos": ""
  },
  {
    "id": "1838865107117334984",
    "name": "李老师不是你老师",
    "accountId": "whyyoutouzhele",
    "sensitive": false,
    "createdDate": "2024-09-25 16:56:20",
    "content": "经历了几轮反转之后，小粉红的心理状态会产生变化吗？ https://t.co/zjtHjZWLJl",
    "images": "/tweet/image/whyyoutouzhele/2024/09/25/1838865107117334984_0.jpg,",
    "videos": "",
    "isReply": false,
    "isRetweet": false,
    "isSelfThread": false,
    "likes": 4207,
    "replies": 270,
    "retweets": 493,
    "views": 1017726,
    "originVideos": ""
  },
  {
    "id": "1838864477510422535",
    "name": "李老师不是你老师",
    "accountId": "whyyoutouzhele",
    "sensitive": false,
    "createdDate": "2024-09-25 16:53:50",
    "content": "9月23日，王毅会见黎巴嫩外长，称无论局势如何变化，都会坚持站在正义一边，站在包括黎巴嫩在内的阿拉伯兄弟一边。 https://t.co/S4hp1m4p1p",
    "images": "",
    "videos": "/tweet/video/whyyoutouzhele/2024/09/25/1838864477510422535_0.jpg,",
    "isReply": false,
    "isRetweet": false,
    "isSelfThread": false,
    "likes": 1003,
    "replies": 382,
    "retweets": 104,
    "views": 338702,
    "originVideos": "https://video.twimg.com/ext_tw_video/1838862589406633984/pu/vid/avc1/592x1280/OX1dvio0sV2c2FK2.mp4?tag=12,"
  },
  {
    "id": "1838861139054060011",
    "name": "李老师不是你老师",
    "accountId": "whyyoutouzhele",
    "sensitive": false,
    "createdDate": "2024-09-25 16:40:34",
    "content": "9月24日，王毅在联合国安理会上表示，任何在俄乌问题上抹黑中国的做法都不会得逞 https://t.co/R3NHkMQVBX",
    "images": "",
    "videos": "/tweet/video/whyyoutouzhele/2024/09/25/1838861139054060011_0.jpg,",
    "isReply": false,
    "isRetweet": false,
    "isSelfThread": false,
    "likes": 689,
    "replies": 313,
    "retweets": 60,
    "views": 252277,
    "originVideos": "https://video.twimg.com/ext_tw_video/1838861047534374912/pu/vid/avc1/592x1280/HkJyW-ktRrXPs_wL.mp4?tag=12,"
  },
  {
    "id": "1838859389387649447",
    "name": "李老师不是你老师",
    "accountId": "whyyoutouzhele",
    "sensitive": false,
    "createdDate": "2024-09-25 16:33:37",
    "content": "网友补充一些酒店和民宿房间内隐藏摄像头的内幕： https://t.co/xmjghxb40m",
    "images": "/tweet/image/whyyoutouzhele/2024/09/25/1838859389387649447_0.jpg,/tweet/image/whyyoutouzhele/2024/09/25/1838859389387649447_1.jpg,/tweet/image/whyyoutouzhele/2024/09/25/1838859389387649447_2.jpg,/tweet/image/whyyoutouzhele/2024/09/25/1838859389387649447_3.jpg,",
    "videos": "",
    "isReply": false,
    "isRetweet": false,
    "isSelfThread": false,
    "likes": 2759,
    "replies": 87,
    "retweets": 481,
    "views": 1678682,
    "originVideos": ""
  },
  {
    "id": "1838925064802070547",
    "name": "李老师不是你老师",
    "accountId": "whyyoutouzhele",
    "sensitive": false,
    "createdDate": "2024-09-25 20:54:35",
    "content": "9月25日（发布），某视频博主，在抖音读了一段《中国哲学简史》的第一章后，直播间竟然被抖音官方封禁，咨询抖音官方客服得到的回答是不建议不鼓励在抖音传播文化和知识。 https://t.co/9gnfAps7jZ",
    "images": "",
    "videos": "/tweet/video/whyyoutouzhele/2024/09/25/1838925064802070547_0.jpg,",
    "isReply": false,
    "isRetweet": false,
    "isSelfThread": false,
    "likes": 3443,
    "replies": 271,
    "retweets": 493,
    "views": 711829,
    "originVideos": "https://video.twimg.com/ext_tw_video/1838924961156575232/pu/vid/avc1/888x540/oYvy_rycIST5w4Y9.mp4?tag=12,"
  },
  {
    "id": "1838921589078778276",
    "name": "李老师不是你老师",
    "accountId": "whyyoutouzhele",
    "sensitive": false,
    "createdDate": "2024-09-25 20:40:47",
    "content": "9月24日，安徽合肥，一女子在12楼外墙维修防水时，一老人因不满自家不锈钢外窗被弄脏，在家中拿刀切割女子的安全绳。 https://t.co/LyObSRdmFX",
    "images": "/tweet/image/whyyoutouzhele/2024/09/25/1838921589078778276_0.jpg,/tweet/image/whyyoutouzhele/2024/09/25/1838921589078778276_1.jpg,/tweet/image/whyyoutouzhele/2024/09/25/1838921589078778276_2.jpg,/tweet/image/whyyoutouzhele/2024/09/25/1838921589078778276_3.jpg,",
    "videos": "",
    "isReply": false,
    "isRetweet": false,
    "isSelfThread": false,
    "likes": 1715,
    "replies": 215,
    "retweets": 141,
    "views": 673923,
    "originVideos": ""
  },
  {
    "id": "1838918542323823061",
    "name": "李老师不是你老师",
    "accountId": "whyyoutouzhele",
    "sensitive": false,
    "createdDate": "2024-09-25 20:28:40",
    "content": "9月18日，浙江树人学院发通知，要求每个学生观看“大思政”公益课网络直播，并拍照打卡，还要写心得体会。 https://t.co/F2PO6Z8fuj",
    "images": "/tweet/image/whyyoutouzhele/2024/09/25/1838918542323823061_0.jpg,",
    "videos": "",
    "isReply": false,
    "isRetweet": false,
    "isSelfThread": false,
    "likes": 463,
    "replies": 61,
    "retweets": 45,
    "views": 202554,
    "originVideos": ""
  },
  {
    "id": "1838903015882764643",
    "name": "李老师不是你老师",
    "accountId": "whyyoutouzhele",
    "sensitive": false,
    "createdDate": "2024-09-25 19:26:58",
    "content": "9月24日，彭博社发文 《Xi’s Economic Adrenaline Shot Is Only Buying China a Little Time(习的经济刺激只是为中国争取了一点时间)》\n\n周二匆忙安排的简报会提出了一个全面的政策方案。经济学家表示，扭转衰退需要更多。\n\n宏观经济学首席中国经济学家邓肯表示：“我认为，这不足以解决中国滑向通缩螺旋背后的根本问题。”他补充称，中国需要的是“一揽子改革，从根本上重新配置经济，释放消费增长。”\n\n据知情人士透露，在习政府的高层领导人在几周内越来越焦虑之后，周二的新闻发布会召开了。共产党高层领导人的迅速转变令许多官员感到意外。他们为重振经济而拟定的政策建议，已经等了好几个月才得到任何反馈。\n\n原文是英文，截图为中文译文",
    "images": "/tweet/image/whyyoutouzhele/2024/09/25/1838903015882764643_0.jpg,/tweet/image/whyyoutouzhele/2024/09/25/1838903015882764643_1.jpg,/tweet/image/whyyoutouzhele/2024/09/25/1838903015882764643_2.jpg,/tweet/image/whyyoutouzhele/2024/09/25/1838903015882764643_3.jpg,",
    "videos": "",
    "isReply": false,
    "isRetweet": false,
    "isSelfThread": false,
    "likes": 2610,
    "replies": 194,
    "retweets": 340,
    "views": 1922634,
    "originVideos": ""
  },
  {
    "id": "1838883415728279718",
    "name": "李老师不是你老师",
    "accountId": "whyyoutouzhele",
    "sensitive": false,
    "createdDate": "2024-09-25 18:09:05",
    "content": "9月20日，北京国际音乐节宣布，本场音乐节的重要演出，清唱剧《上海！上海！》被北京市主管部门以“特殊原因”为由建议暂停演出。\n该剧讲述遭受纳粹迫害的犹太难民约瑟夫和奥托两兄弟，在陌生的异乡开启全新生活，并与上海姑娘发生刻骨铭心的爱情故事。 https://t.co/sGRg0zALPe",
    "images": "/tweet/image/whyyoutouzhele/2024/09/25/1838883415728279718_0.jpg,",
    "videos": "",
    "isReply": false,
    "isRetweet": false,
    "isSelfThread": false,
    "likes": 1075,
    "replies": 106,
    "retweets": 84,
    "views": 308459,
    "originVideos": ""
  },
  {
    "id": "1838875918481211504",
    "name": "李老师不是你老师",
    "accountId": "whyyoutouzhele",
    "sensitive": false,
    "createdDate": "2024-09-25 17:39:18",
    "content": "有网友根据山东省菏泽市成武县发布的《2023年国民经济和社会发展统计公报》中的数据统计后发现，2023年全县领取养老金总人口有14万人，发放养老金14亿元。\n其中8778名机关单位退休人员领取了全县55.93%的养老金，体制内年均领取的养老金金额约是当地普通城乡居民的42倍。 https://t.co/01WHHL8bAS",
    "images": "/tweet/image/whyyoutouzhele/2024/09/25/1838875918481211504_0.jpg,/tweet/image/whyyoutouzhele/2024/09/25/1838875918481211504_1.jpg,/tweet/image/whyyoutouzhele/2024/09/25/1838875918481211504_2.jpg,/tweet/image/whyyoutouzhele/2024/09/25/1838875918481211504_3.jpg,",
    "videos": "",
    "isReply": false,
    "isRetweet": false,
    "isSelfThread": false,
    "likes": 1836,
    "replies": 110,
    "retweets": 349,
    "views": 380901,
    "originVideos": ""
  },
  {
    "id": "1838870866144252286",
    "name": "李老师不是你老师",
    "accountId": "whyyoutouzhele",
    "sensitive": false,
    "createdDate": "2024-09-25 17:19:13",
    "content": "9月24日，一名抖音用户发视频称，因为听说苹果手机会爆炸，这几天把全家的苹果手机都砸了 https://t.co/1AjKXo3GQB",
    "images": "",
    "videos": "/tweet/video/whyyoutouzhele/2024/09/25/1838870866144252286_0.jpg,",
    "isReply": false,
    "isRetweet": false,
    "isSelfThread": false,
    "likes": 3075,
    "replies": 1006,
    "retweets": 270,
    "views": 844567,
    "originVideos": "https://video.twimg.com/ext_tw_video/1838870489961230336/pu/vid/avc1/720x1280/59rI3Rq6YELfW4r3.mp4?tag=12,"
  },
  {
    "id": "1838943457697562777",
    "name": "李老师不是你老师",
    "accountId": "whyyoutouzhele",
    "sensitive": false,
    "createdDate": "2024-09-25 22:07:40",
    "content": "据悉，上海银行的营收已经连续两年下滑，净利润也只能维持低速增长，以2023年的营收为例，上海银行已经掉到城商行第四的位置，营收只有江苏银行的68%左右。2023年人均薪酬同比下降7.4万元，降幅“遥遥领先”。 https://t.co/fVuKBOKJuC",
    "images": "/tweet/image/whyyoutouzhele/2024/09/25/1838943457697562777_0.jpg,/tweet/image/whyyoutouzhele/2024/09/25/1838943457697562777_1.jpg,/tweet/image/whyyoutouzhele/2024/09/25/1838943457697562777_2.jpg,",
    "videos": "",
    "isReply": true,
    "isRetweet": false,
    "isSelfThread": false,
    "likes": 335,
    "replies": 19,
    "retweets": 21,
    "views": 153597,
    "originVideos": ""
  },
  {
    "id": "1838940973977448610",
    "name": "李老师不是你老师",
    "accountId": "whyyoutouzhele",
    "sensitive": false,
    "createdDate": "2024-09-25 21:57:48",
    "content": "9月25日，某大学信息工程系在学生并不知情的情况下选举出了学生代表与学生会干部，有学生发邮件表达质疑。 https://t.co/rJz26hnTL4",
    "images": "/tweet/image/whyyoutouzhele/2024/09/25/1838940973977448610_0.jpg,/tweet/image/whyyoutouzhele/2024/09/25/1838940973977448610_1.jpg,",
    "videos": "",
    "isReply": false,
    "isRetweet": false,
    "isSelfThread": false,
    "likes": 921,
    "replies": 99,
    "retweets": 71,
    "views": 325472,
    "originVideos": ""
  },
  {
    "id": "1838936485589811204",
    "name": "李老师不是你老师",
    "accountId": "whyyoutouzhele",
    "sensitive": false,
    "createdDate": "2024-09-25 21:39:58",
    "content": "继9月初上海银行被曝出天津分行党委书记于枫调换员工考核结果后，原举报人今日又在朋友圈历数前分行班子成员王昱炜在获得高管资格时“暗箱操作”、“德不配位”的经过，以及几任天津分行党委书记能成为“一把手”的鲜为人知的“上位”手段。 https://t.co/cqaNROWsFp",
    "images": "/tweet/image/whyyoutouzhele/2024/09/25/1838936485589811204_0.jpg,/tweet/image/whyyoutouzhele/2024/09/25/1838936485589811204_1.jpg,",
    "videos": "",
    "isReply": false,
    "isRetweet": false,
    "isSelfThread": false,
    "likes": 567,
    "replies": 50,
    "retweets": 63,
    "views": 332175,
    "originVideos": ""
  },
  {
    "id": "1838932828932702215",
    "name": "李老师不是你老师",
    "accountId": "whyyoutouzhele",
    "sensitive": false,
    "createdDate": "2024-09-25 21:25:26",
    "content": "9月24日，据南方都市报报道，自2020年制定《广州市政务服务“好差评”实施细则》以来，广州市通过建立多维度政务信息化评估体系，并将效能评估结果与政务信息化项目立项“挂钩”，“倒逼”市级政务信息化项目效能提升。\n广东省政务服务网最新数据统计显示，今年截至9月24日，广州市各区各单位接受评价总数为22264351条，差评数为78条。其中增城区收到差评23条，系广州11区中差评数量最多的行政区。",
    "images": "/tweet/image/whyyoutouzhele/2024/09/25/1838932828932702215_0.jpg,/tweet/image/whyyoutouzhele/2024/09/25/1838932828932702215_1.jpg,/tweet/image/whyyoutouzhele/2024/09/25/1838932828932702215_2.jpg,/tweet/image/whyyoutouzhele/2024/09/25/1838932828932702215_3.jpg,",
    "videos": "",
    "isReply": false,
    "isRetweet": false,
    "isSelfThread": false,
    "likes": 345,
    "replies": 41,
    "retweets": 23,
    "views": 191926,
    "originVideos": ""
  },
  {
    "id": "1838930241831485745",
    "name": "李老师不是你老师",
    "accountId": "whyyoutouzhele",
    "sensitive": false,
    "createdDate": "2024-09-25 21:15:09",
    "content": "经查，这是一条2022年的旧闻。 https://t.co/IFJabZmnCG",
    "images": "/tweet/image/whyyoutouzhele/2024/09/25/1838930241831485745_0.jpg,",
    "videos": "",
    "isReply": true,
    "isRetweet": false,
    "isSelfThread": false,
    "likes": 762,
    "replies": 29,
    "retweets": 31,
    "views": 208119,
    "originVideos": ""
  }
]