[
  {
    "id": "1923050070745940354",
    "name": "李老师不是你老师",
    "accountId": "whyyoutouzhele",
    "sensitive": false,
    "createdDate": "2025-05-16 00:17:20",
    "content": "5月15日，河南。女子向中央巡视组反映，自己19岁的孩子失踪两个多月了“就像人间蒸发一样”突然不见了，并且报案后警方至今未立案，我作为一个母亲现在精神快崩溃了。中央巡视组：不属于巡视的范围 https://t.co/NjPgu8xDRZ",
    "images": "",
    "videos": "/tweet/video/whyyoutouzhele/2025/05/16/1923050070745940354_0.jpg,/tweet/video/whyyoutouzhele/2025/05/16/1923050070745940354_1.jpg,",
    "isReply": false,
    "isRetweet": false,
    "isSelfThread": false,
    "likes": 1023,
    "replies": 300,
    "retweets": 197,
    "views": 212794,
    "originVideos": "https://video.twimg.com/amplify_video/1923046135381282816/vid/avc1/376x728/McwmLKWQweE16jCA.mp4?tag=21,https://video.twimg.com/amplify_video/1923049635108487177/vid/avc1/480x930/0yNrTMP43de2tsTr.mp4?tag=21,"
  },
  {
    "id": "1923062202472464800",
    "name": "李老师不是你老师",
    "accountId": "whyyoutouzhele",
    "sensitive": false,
    "createdDate": "2025-05-16 01:05:32",
    "content": "【中国外交部：中方不同意台湾参加今年的世卫大会】世界卫生组织大会将于19日在瑞士日内瓦召开。台湾外交部日前表示，至今世卫组织还是基于政治因素，并没有邀请台湾出席世卫大会。台外交部国际组织司副司长张芝飒批评中国刻意且有系统地错误诠释联大第2758号决议，矮化台湾为中国一部分，排除台湾参与 https://t.co/lhUSlb0Lhy",
    "images": "/tweet/image/whyyoutouzhele/2025/05/16/1923062202472464800_0.jpg,",
    "videos": "/tweet/video/whyyoutouzhele/2025/05/16/1923062202472464800_0.jpg,",
    "isReply": false,
    "isRetweet": false,
    "isSelfThread": false,
    "likes": 254,
    "replies": 192,
    "retweets": 19,
    "views": 110241,
    "originVideos": "https://video.twimg.com/amplify_video/1923061448126742528/vid/avc1/1080x1920/JjdaL5BbOImJ3Pxa.mp4?tag=21,"
  },
  {
    "id": "1923072402902352034",
    "name": "李老师不是你老师",
    "accountId": "whyyoutouzhele",
    "sensitive": false,
    "createdDate": "2025-05-16 01:46:04",
    "content": "5月15日 一位博主称，一则煤炭行业的报告中提到“收获来自煤矿石以及击杀凋零骷髅获得1-3个”而“凋零骷髅”来自游戏《我的世界》 https://t.co/Dgk9dSt2ZW",
    "images": "/tweet/image/whyyoutouzhele/2025/05/16/1923072402902352034_0.jpg,",
    "videos": "/tweet/video/whyyoutouzhele/2025/05/16/1923072402902352034_0.jpg,/tweet/video/whyyoutouzhele/2025/05/16/1923072402902352034_1.jpg,",
    "isReply": false,
    "isRetweet": false,
    "isSelfThread": false,
    "likes": 1098,
    "replies": 164,
    "retweets": 103,
    "views": 220520,
    "originVideos": "https://video.twimg.com/amplify_video/1923072071841538048/vid/avc1/1080x1920/bkLhL54GEInv1F0r.mp4?tag=21,https://video.twimg.com/amplify_video/1923072093199241216/vid/avc1/1080x1920/06m0RxmsGLldZwIr.mp4?tag=21,"
  },
  {
    "id": "1923082712815985006",
    "name": "李老师不是你老师",
    "accountId": "whyyoutouzhele",
    "sensitive": false,
    "createdDate": "2025-05-16 02:27:02",
    "content": "在美国当过医生的神经外科刘柏麟教授称，董小姐的4+4只能算医学临床本科水平，不能简单等同于5+3+3出来的医学博士。\n 不过董小姐入学协和医学院两年，便上手术台参与荧光腔镜精准肺段手术，而且入学资格还是造假的 https://t.co/Eu2qzPb96S",
    "images": "/tweet/image/whyyoutouzhele/2025/05/16/1923082712815985006_0.jpg,",
    "videos": "/tweet/video/whyyoutouzhele/2025/05/16/1923082712815985006_0.jpg,",
    "isReply": true,
    "isRetweet": false,
    "isSelfThread": false,
    "likes": 212,
    "replies": 13,
    "retweets": 9,
    "views": 79103,
    "originVideos": "https://video.twimg.com/amplify_video/1923082371722575872/vid/avc1/1920x1080/vhWbBqzyFYsELsty.mp4?tag=21,"
  },
  {
    "id": "1923091638127149539",
    "name": "李老师不是你老师",
    "accountId": "whyyoutouzhele",
    "sensitive": false,
    "createdDate": "2025-05-16 03:02:30",
    "content": "5月15日，广西博白县。\n绿柏村村民阻止中国能源建设集团广东火电工程有限公司挖山。 https://t.co/O37pu9uuMw",
    "images": "",
    "videos": "/tweet/video/whyyoutouzhele/2025/05/16/1923091638127149539_0.jpg,/tweet/video/whyyoutouzhele/2025/05/16/1923091638127149539_1.jpg,",
    "isReply": false,
    "isRetweet": false,
    "isSelfThread": false,
    "likes": 170,
    "replies": 103,
    "retweets": 7,
    "views": 68589,
    "originVideos": "https://video.twimg.com/amplify_video/1923090726671253504/vid/avc1/544x960/O8RGlOc1eSTMOznV.mp4?tag=21,https://video.twimg.com/amplify_video/1923090731951923200/vid/avc1/544x960/UPgNxriho08bC70u.mp4?tag=21,"
  },
  {
    "id": "1923095458571755561",
    "name": "李老师不是你老师",
    "accountId": "whyyoutouzhele",
    "sensitive": false,
    "createdDate": "2025-05-16 03:17:41",
    "content": "5月15日，江西上饶。烂尾楼业主跳楼维权 https://t.co/jvJesa9HEj",
    "images": "",
    "videos": "/tweet/video/whyyoutouzhele/2025/05/16/1923095458571755561_0.jpg,",
    "isReply": false,
    "isRetweet": false,
    "isSelfThread": false,
    "likes": 228,
    "replies": 64,
    "retweets": 12,
    "views": 70321,
    "originVideos": "https://video.twimg.com/amplify_video/1923095106720067584/vid/avc1/576x1024/JJFapDUKC48pXBWo.mp4?tag=21,"
  },
  {
    "id": "1923098930344067473",
    "name": "李老师不是你老师",
    "accountId": "whyyoutouzhele",
    "sensitive": false,
    "createdDate": "2025-05-16 03:31:29",
    "content": "5月15日，广东深圳。全利玩具厂欠薪半年，工人们堵门讨薪 https://t.co/OnI0vFjVnX",
    "images": "",
    "videos": "/tweet/video/whyyoutouzhele/2025/05/16/1923098930344067473_0.jpg,",
    "isReply": false,
    "isRetweet": false,
    "isSelfThread": false,
    "likes": 344,
    "replies": 52,
    "retweets": 32,
    "views": 87917,
    "originVideos": "https://video.twimg.com/amplify_video/1923098741742972928/vid/avc1/720x1280/qfOCoOaKibEhBSOH.mp4?tag=21,"
  },
  {
    "id": "1923103416634458228",
    "name": "李老师不是你老师",
    "accountId": "whyyoutouzhele",
    "sensitive": false,
    "createdDate": "2025-05-16 03:49:18",
    "content": "5月15日，湖南株洲。\n大唐华银电力股份有限公司拖欠工资，工人维权 https://t.co/CycQ8icMcs",
    "images": "/tweet/image/whyyoutouzhele/2025/05/16/1923103416634458228_0.jpg,/tweet/image/whyyoutouzhele/2025/05/16/1923103416634458228_1.jpg,",
    "videos": "/tweet/video/whyyoutouzhele/2025/05/16/1923103416634458228_0.jpg,",
    "isReply": false,
    "isRetweet": false,
    "isSelfThread": false,
    "likes": 259,
    "replies": 47,
    "retweets": 15,
    "views": 93124,
    "originVideos": "https://video.twimg.com/amplify_video/1923102994163183616/vid/avc1/576x1024/lTC8aoA3lLiVfEU6.mp4?tag=21,"
  },
  {
    "id": "1923111096476475703",
    "name": "李老师不是你老师",
    "accountId": "whyyoutouzhele",
    "sensitive": false,
    "createdDate": "2025-05-16 04:19:49",
    "content": "5月15日，广西百色。\n龙旺商业广场烂尾楼用户就烂尾楼问题交涉无果，选择“跳楼”维权 https://t.co/8rGvQHhG5y",
    "images": "",
    "videos": "/tweet/video/whyyoutouzhele/2025/05/16/1923111096476475703_0.jpg,/tweet/video/whyyoutouzhele/2025/05/16/1923111096476475703_1.jpg,",
    "isReply": false,
    "isRetweet": false,
    "isSelfThread": false,
    "likes": 231,
    "replies": 60,
    "retweets": 13,
    "views": 75092,
    "originVideos": "https://video.twimg.com/amplify_video/1923110738182176768/vid/avc1/576x1024/mdHdcIH04SUFMa3l.mp4?tag=21,https://video.twimg.com/amplify_video/1923110745299906560/vid/avc1/720x1280/uXaBBlo3XfDUuZTl.mp4?tag=21,"
  },
  {
    "id": "1923111483656864186",
    "name": "李老师不是你老师",
    "accountId": "whyyoutouzhele",
    "sensitive": false,
    "createdDate": "2025-05-16 04:21:22",
    "content": "5月15日，广东深圳。\n中城南方建设集团，潭罗村工地，农民工讨薪维权 https://t.co/GO6OhDsk5m",
    "images": "/tweet/image/whyyoutouzhele/2025/05/16/1923111483656864186_0.jpg,",
    "videos": "/tweet/video/whyyoutouzhele/2025/05/16/1923111483656864186_0.jpg,",
    "isReply": false,
    "isRetweet": false,
    "isSelfThread": false,
    "likes": 227,
    "replies": 47,
    "retweets": 8,
    "views": 80804,
    "originVideos": "https://video.twimg.com/amplify_video/1923110937889841152/vid/avc1/720x1280/wp5ZlOCVLjapzlO5.mp4?tag=21,"
  },
  {
    "id": "1923115525837619459",
    "name": "李老师不是你老师",
    "accountId": "whyyoutouzhele",
    "sensitive": false,
    "createdDate": "2025-05-16 04:37:25",
    "content": "5月14日，广西崇左有网友曝光，县里突然要求上报教师办理了护照的名单。\n有黄果树网友称，去年黄果树就已经这样接龙，之后护照统一交给了教育局，什么文件都没有发下来。 https://t.co/iXiPvoWDSR",
    "images": "/tweet/image/whyyoutouzhele/2025/05/16/1923115525837619459_0.jpg,/tweet/image/whyyoutouzhele/2025/05/16/1923115525837619459_1.jpg,/tweet/image/whyyoutouzhele/2025/05/16/1923115525837619459_2.jpg,/tweet/image/whyyoutouzhele/2025/05/16/1923115525837619459_3.jpg,",
    "videos": "",
    "isReply": false,
    "isRetweet": false,
    "isSelfThread": false,
    "likes": 375,
    "replies": 88,
    "retweets": 23,
    "views": 103560,
    "originVideos": ""
  },
  {
    "id": "1923121356113088615",
    "name": "李老师不是你老师",
    "accountId": "whyyoutouzhele",
    "sensitive": false,
    "createdDate": "2025-05-16 05:00:35",
    "content": "5月15日，广州市黄浦区街道办事处，工人讨薪 https://t.co/AZyWIMxe6x",
    "images": "",
    "videos": "/tweet/video/whyyoutouzhele/2025/05/16/1923121356113088615_0.jpg,",
    "isReply": false,
    "isRetweet": false,
    "isSelfThread": false,
    "likes": 247,
    "replies": 11,
    "retweets": 12,
    "views": 76664,
    "originVideos": "https://video.twimg.com/amplify_video/1923121248537600001/vid/avc1/576x1024/f30Eo9dWrJh-9-NJ.mp4?tag=21,"
  },
  {
    "id": "1923125574177784269",
    "name": "李老师不是你老师",
    "accountId": "whyyoutouzhele",
    "sensitive": false,
    "createdDate": "2025-05-16 05:17:21",
    "content": "5月9日，在一则吐槽社区拖欠工资的帖子下方，尽管全国各地的社区工作人员都表示存在大量拖欠工资的情况，但社区单位依然报名火热。\n“真心想不到2000多工资的岗位这么多人抢”\n“因为擦‘编’” https://t.co/3pCPw2SiSF",
    "images": "/tweet/image/whyyoutouzhele/2025/05/16/1923125574177784269_0.jpg,/tweet/image/whyyoutouzhele/2025/05/16/1923125574177784269_1.jpg,/tweet/image/whyyoutouzhele/2025/05/16/1923125574177784269_2.jpg,/tweet/image/whyyoutouzhele/2025/05/16/1923125574177784269_3.jpg,",
    "videos": "",
    "isReply": false,
    "isRetweet": false,
    "isSelfThread": false,
    "likes": 371,
    "replies": 62,
    "retweets": 36,
    "views": 90140,
    "originVideos": ""
  },
  {
    "id": "1923129572708557088",
    "name": "李老师不是你老师",
    "accountId": "whyyoutouzhele",
    "sensitive": false,
    "createdDate": "2025-05-16 05:33:14",
    "content": "5月15日，有广西体制内透露一直没发工资\n5月7日，佛山南海教师透露年终绩效不发 https://t.co/4Cfj9V3na3",
    "images": "/tweet/image/whyyoutouzhele/2025/05/16/1923129572708557088_0.jpg,/tweet/image/whyyoutouzhele/2025/05/16/1923129572708557088_1.jpg,",
    "videos": "",
    "isReply": false,
    "isRetweet": false,
    "isSelfThread": false,
    "likes": 332,
    "replies": 58,
    "retweets": 33,
    "views": 96428,
    "originVideos": ""
  },
  {
    "id": "1923131769097687199",
    "name": "李老师不是你老师",
    "accountId": "whyyoutouzhele",
    "sensitive": false,
    "createdDate": "2025-05-16 05:41:58",
    "content": "5月15日， CSW 新闻与公共事务官 Ellis Heasley 呼吁中国政府提供十一世班禅更登确吉尼玛的下落。\n1995年，被认定为第十一世班禅的，年仅六岁的更登确吉尼玛被中国当局抓走，成为全球最年轻的政治犯，至今下落不明。\nhttps://t.co/PF2YTzMFn7 https://t.co/rvl9SAlHYv",
    "images": "/tweet/image/whyyoutouzhele/2025/05/16/1923131769097687199_0.jpg,",
    "videos": "",
    "isReply": false,
    "isRetweet": false,
    "isSelfThread": false,
    "likes": 856,
    "replies": 117,
    "retweets": 92,
    "views": 209847,
    "originVideos": ""
  },
  {
    "id": "1923143678253568040",
    "name": "李老师不是你老师",
    "accountId": "whyyoutouzhele",
    "sensitive": false,
    "createdDate": "2025-05-16 06:29:17",
    "content": "风有声 ，鸣自由。",
    "images": "",
    "videos": "",
    "isReply": false,
    "isRetweet": false,
    "isSelfThread": false,
    "likes": 358,
    "replies": 21,
    "retweets": 14,
    "views": 129203,
    "originVideos": ""
  },
  {
    "id": "1923141340042518560",
    "name": "李老师不是你老师",
    "accountId": "whyyoutouzhele",
    "sensitive": false,
    "createdDate": "2025-05-16 06:20:00",
    "content": "5月15日，广东省广州市。\n番禺区大石街道办2022年到2023年的服务费到现在没给，公司几个月没发工资，员工讨薪。 https://t.co/jeafKX6snT",
    "images": "",
    "videos": "/tweet/video/whyyoutouzhele/2025/05/16/1923141340042518560_0.jpg,",
    "isReply": false,
    "isRetweet": false,
    "isSelfThread": false,
    "likes": 380,
    "replies": 107,
    "retweets": 36,
    "views": 112116,
    "originVideos": "https://video.twimg.com/amplify_video/1923095874193723393/vid/avc1/576x1024/nXN7s3uxD17riXqJ.mp4?tag=21,"
  },
  {
    "id": "1923145864064733425",
    "name": "李老师不是你老师",
    "accountId": "whyyoutouzhele",
    "sensitive": false,
    "createdDate": "2025-05-16 06:37:58",
    "content": "https://t.co/kIYpdyk4mh",
    "images": "",
    "videos": "/tweet/video/whyyoutouzhele/2025/05/16/1923145864064733425_0.jpg,",
    "isReply": true,
    "isRetweet": false,
    "isSelfThread": false,
    "likes": 158,
    "replies": 11,
    "retweets": 3,
    "views": 87349,
    "originVideos": "https://video.twimg.com/amplify_video/1923145785408999424/vid/avc1/720x1280/i-zD5qfkkzONgYOD.mp4?tag=21,"
  },
  {
    "id": "1923144863454986384",
    "name": "李老师不是你老师",
    "accountId": "whyyoutouzhele",
    "sensitive": false,
    "createdDate": "2025-05-16 06:34:00",
    "content": "5月15日，海南省海口市。\n翰香村,安久村村民抗议当地征地建设公墓。\n现场大量手持甩棍的安保人员。 https://t.co/XVHMkYwqAa",
    "images": "",
    "videos": "/tweet/video/whyyoutouzhele/2025/05/16/1923144863454986384_0.jpg,",
    "isReply": false,
    "isRetweet": false,
    "isSelfThread": false,
    "likes": 271,
    "replies": 59,
    "retweets": 19,
    "views": 97611,
    "originVideos": "https://video.twimg.com/amplify_video/1923099270858608640/vid/avc1/576x1024/uHQZCYsLEShf_2p6.mp4?tag=21,"
  },
  {
    "id": "1923158958044336326",
    "name": "李老师不是你老师",
    "accountId": "whyyoutouzhele",
    "sensitive": false,
    "createdDate": "2025-05-16 07:30:00",
    "content": "5月15日，宁夏网友透露，基层服务专项计划，从1月份到现在工资没发\n5月15日，吉林长春。网友透露老城区教师绩效一直没发\n5月14日，广西玉林，自聘教师工资一直没有发\n5月10日，陕西。有事业编表示5险1金一直没发，已经拖欠8个月。评论区有西安体制内称4个月还没发工资。 https://t.co/MellxtkVZ8",
    "images": "/tweet/image/whyyoutouzhele/2025/05/16/1923158958044336326_0.jpg,/tweet/image/whyyoutouzhele/2025/05/16/1923158958044336326_1.jpg,/tweet/image/whyyoutouzhele/2025/05/16/1923158958044336326_2.jpg,/tweet/image/whyyoutouzhele/2025/05/16/1923158958044336326_3.jpg,",
    "videos": "",
    "isReply": false,
    "isRetweet": false,
    "isSelfThread": false,
    "likes": 460,
    "replies": 123,
    "retweets": 45,
    "views": 122759,
    "originVideos": ""
  },
  {
    "id": "1923170280496824779",
    "name": "李老师不是你老师",
    "accountId": "whyyoutouzhele",
    "sensitive": false,
    "createdDate": "2025-05-16 08:15:00",
    "content": "这段时间，搞笑网红“重庆光棍哥”在网上爆火\n其视频内容主打“躺平”概念，组织一帮大龄光棍隐居深山，强调拒绝内卷，拒绝婚姻，不当牛马，快乐生活。\n然而就在5月15日，光棍哥宣布，因“不可抗力因素”，光棍山庄解散。 https://pbs.twimg.com/amplify_video_thumb/1923092483526848512/img/dGxrG026m7NoQYoy.jpg",
    "images": "",
    "videos": "/tweet/video/whyyoutouzhele/2025/05/16/1923170280496824779_0.jpg,/tweet/video/whyyoutouzhele/2025/05/16/1923170280496824779_1.jpg,/tweet/video/whyyoutouzhele/2025/05/16/1923170280496824779_2.jpg,/tweet/video/whyyoutouzhele/2025/05/16/1923170280496824779_3.jpg,",
    "isReply": false,
    "isRetweet": false,
    "isSelfThread": false,
    "likes": 2573,
    "replies": 472,
    "retweets": 292,
    "views": 1561268,
    "originVideos": "https://video.twimg.com/amplify_video/1923092483526848512/vid/avc1/720x1280/HeyIw2NHNkNiV9rl.mp4?tag=21,https://video.twimg.com/amplify_video/1923092490317398016/vid/avc1/720x1280/P_kZEyQA8JN1DpKT.mp4?tag=21,https://video.twimg.com/amplify_video/1923092514308808704/vid/avc1/576x1024/ZMo8_2UJkbORZTcD.mp4?tag=21,https://video.twimg.com/amplify_video/1923092521309118464/vid/avc1/720x1280/RswXIJAdNjPUSvG_.mp4?tag=21,"
  },
  {
    "id": "1923227201551405295",
    "name": "李老师不是你老师",
    "accountId": "whyyoutouzhele",
    "sensitive": false,
    "createdDate": "2025-05-16 12:01:11",
    "content": "5月15日 贵州仁怀网友表示，有顾客购买的正新鸡排鸡腿面皮底下全是蛆。经过搜索发现这似乎不是个例，过去几年抖音上有多起全国各地网友曝光正新鸡排有蛆或者虫卵的投诉视频。 https://pbs.twimg.com/amplify_video_thumb/1923226134243835909/img/jcQ1N9aROA4ynztg.jpg",
    "images": "/tweet/image/whyyoutouzhele/2025/05/16/1923227201551405295_0.jpg,",
    "videos": "/tweet/video/whyyoutouzhele/2025/05/16/1923227201551405295_0.jpg,",
    "isReply": false,
    "isRetweet": false,
    "isSelfThread": false,
    "likes": 1060,
    "replies": 364,
    "retweets": 172,
    "views": 192734,
    "originVideos": "https://video.twimg.com/amplify_video/1923226134243835909/vid/avc1/720x1280/3CPCZuEdJWc60j-5.mp4?tag=21,"
  },
  {
    "id": "1923231032507093261",
    "name": "李老师不是你老师",
    "accountId": "whyyoutouzhele",
    "sensitive": false,
    "createdDate": "2025-05-16 12:16:24",
    "content": "5月16日 因银行强行要求患病老人亲自前往银行柜台办理业务，并且一个多小时还没办好导致老人在银行取款身亡事件，家属和银行达成和解。\n银行方面将负责老人的丧葬费用，以慰问金的形式向家属支付10万元。 https://pbs.twimg.com/media/GrCv72aaAAMC7bK.jpg",
    "images": "/tweet/image/whyyoutouzhele/2025/05/16/1923231032507093261_0.jpg,",
    "videos": "",
    "isReply": false,
    "isRetweet": false,
    "isSelfThread": false,
    "likes": 521,
    "replies": 187,
    "retweets": 69,
    "views": 163362,
    "originVideos": ""
  },
  {
    "id": "1923241409890455654",
    "name": "李老师不是你老师",
    "accountId": "whyyoutouzhele",
    "sensitive": false,
    "createdDate": "2025-05-16 12:57:38",
    "content": "黄杨钿甜于今年5月分享成人礼照片，佩戴价值230万元的Graff祖母绿耳环，称“耳环是妈妈的”。\n有网友称其父杨伟曾任四川慈善总会办公室主任，参与13年雅安地震的慈善重建项目。2014年，其父通过小舅子名义开设娱乐公司，后于17年辞去公职接任法人并持股80%。\n其父20年疫情期间还成立了生物科技公司。 https://pbs.twimg.com/media/GrC3p3aaAAAgq48.jpg",
    "images": "/tweet/image/whyyoutouzhele/2025/05/16/1923241409890455654_0.jpg,",
    "videos": "",
    "isReply": true,
    "isRetweet": false,
    "isSelfThread": false,
    "likes": 811,
    "replies": 104,
    "retweets": 70,
    "views": 976294,
    "originVideos": ""
  },
  {
    "id": "1923236782847508615",
    "name": "李老师不是你老师",
    "accountId": "whyyoutouzhele",
    "sensitive": false,
    "createdDate": "2025-05-16 12:39:15",
    "content": "近日 演员黄杨钿甜的低调奢侈生活引发争议，有网友曝光她父亲曾是雅安市负责招投标的公务员。\n据其微博流出的照片显示，黄杨钿甜似乎居住在深圳华侨城的临水别墅，周边别墅的价格在上千万甚至破亿。她母亲的耳环项链加手镯总售价接近百万。\n有雅安人吐槽，当年震后重建都是自己出钱，政府没有出一分钱 https://pbs.twimg.com/media/GrC1aBCb0AAOOTd.jpg",
    "images": "/tweet/image/whyyoutouzhele/2025/05/16/1923236782847508615_0.jpg,/tweet/image/whyyoutouzhele/2025/05/16/1923236782847508615_1.jpg,/tweet/image/whyyoutouzhele/2025/05/16/1923236782847508615_2.jpg,/tweet/image/whyyoutouzhele/2025/05/16/1923236782847508615_3.jpg,",
    "videos": "",
    "isReply": false,
    "isRetweet": false,
    "isSelfThread": false,
    "likes": 1445,
    "replies": 282,
    "retweets": 215,
    "views": 284429,
    "originVideos": ""
  },
  {
    "id": "1923232935437582545",
    "name": "李老师不是你老师",
    "accountId": "whyyoutouzhele",
    "sensitive": false,
    "createdDate": "2025-05-16 12:23:58",
    "content": "5月12日 有网友在西安老义烤肉（盛龙广场）吃饭时，拍到店内服务员将掉落在泔水桶的肉串拿出，后放置在其他肉串上一起烧烤。\n商家和当地市监局称“店员捋好了放在那以后，不到1分钟时间，他又全部捋到垃圾箱里去了。监控录像显示，这些肉串没有被售卖。”\n商家随后发布道歉视频，但目前已被删除。 https://pbs.twimg.com/media/GrCxUXTaAAA3HoD.jpg",
    "images": "/tweet/image/whyyoutouzhele/2025/05/16/1923232935437582545_0.jpg,/tweet/image/whyyoutouzhele/2025/05/16/1923232935437582545_1.jpg,",
    "videos": "",
    "isReply": false,
    "isRetweet": false,
    "isSelfThread": false,
    "likes": 448,
    "replies": 116,
    "retweets": 49,
    "views": 94956,
    "originVideos": ""
  },
  {
    "id": "1923243187151192313",
    "name": "李老师不是你老师",
    "accountId": "whyyoutouzhele",
    "sensitive": false,
    "createdDate": "2025-05-16 13:04:42",
    "content": "https://x.com/whyyoutouzhele/status/1923243094465708215",
    "images": "",
    "videos": "",
    "isReply": true,
    "isRetweet": false,
    "isSelfThread": false,
    "likes": 189,
    "replies": 4,
    "retweets": 12,
    "views": 186736,
    "originVideos": ""
  },
  {
    "id": "1923243094465708215",
    "name": "李老师不是你老师",
    "accountId": "whyyoutouzhele",
    "sensitive": false,
    "createdDate": "2025-05-16 13:04:20",
    "content": "15 董晓军\n#八九民运 #六四屠杀 董晓军，20岁，中国青年政治学院青年工作系86级学生。1989年6月4日清晨，在六部口附近，董晓军走在从天安门广场撤出的学生队伍的尾部，在没有任何防备的情况下，被从后面开来的坦克轧死，尸体被碾得血肉模糊，不成形状。\n董晓军 https://pbs.twimg.com/media/GrC7RCXaAAAjW7O.jpg",
    "images": "/tweet/image/whyyoutouzhele/2025/05/16/1923243094465708215_0.jpg,",
    "videos": "",
    "isReply": false,
    "isRetweet": false,
    "isSelfThread": false,
    "likes": 250,
    "replies": 34,
    "retweets": 40,
    "views": 254330,
    "originVideos": ""
  },
  {
    "id": "1923242151946637359",
    "name": "李老师不是你老师",
    "accountId": "whyyoutouzhele",
    "sensitive": false,
    "createdDate": "2025-05-16 13:00:35",
    "content": "5月15日，河南项城。男子称，母亲近日在项城人民医院“做了一个小小的肾结石微创手术”母亲被推出来时重度昏迷，现在处于脑死亡状态。男子不解为何一个微创手术能致人脑死亡，并且事发十天了，医院一直推诿找理由“我只想让医院还我们一个公道” https://pbs.twimg.com/amplify_video_thumb/1923241010223775746/img/06lZeAkN7qRtT8qt.jpg",
    "images": "",
    "videos": "/tweet/video/whyyoutouzhele/2025/05/16/1923242151946637359_0.jpg,/tweet/video/whyyoutouzhele/2025/05/16/1923242151946637359_1.jpg,",
    "isReply": false,
    "isRetweet": false,
    "isSelfThread": false,
    "likes": 527,
    "replies": 167,
    "retweets": 68,
    "views": 125628,
    "originVideos": "https://video.twimg.com/amplify_video/1923241010223775746/vid/avc1/1280x720/L1GwNsm5Exf87FhK.mp4?tag=21,https://video.twimg.com/amplify_video/1923241018725629954/vid/avc1/1280x720/SURvl38TcsErNsAw.mp4?tag=21,"
  },
  {
    "id": "1923258568272142793",
    "name": "李老师不是你老师",
    "accountId": "whyyoutouzhele",
    "sensitive": false,
    "createdDate": "2025-05-16 14:05:49",
    "content": "5月15日(发布) 男子来到静安区大宁路一家商场，商场地下一层只有一家台球厅还在营业，但店长说因租金问题“马上就要闭馆了” 而商场一层的商铺也大多处于关闭状态，整个商场空空荡荡。男子表示“这可是市区啊” https://pbs.twimg.com/amplify_video_thumb/1923256803166650369/img/DePknETnczeKkYqD.jpg",
    "images": "",
    "videos": "/tweet/video/whyyoutouzhele/2025/05/16/1923258568272142793_0.jpg,",
    "isReply": false,
    "isRetweet": false,
    "isSelfThread": false,
    "likes": 701,
    "replies": 232,
    "retweets": 80,
    "views": 177743,
    "originVideos": "https://video.twimg.com/amplify_video/1923256803166650369/vid/avc1/480x852/_RRY_oJZh6QJAebw.mp4?tag=21,"
  },
  {
    "id": "1923272690200178773",
    "name": "李老师不是你老师",
    "accountId": "whyyoutouzhele",
    "sensitive": false,
    "createdDate": "2025-05-16 15:01:56",
    "content": "5月14日，视频显示，数十名城管动作干净利索，仅用半分钟就把摆放在店外的水果全部“清空”搬到车上。商家和城管发生肢体冲突，并大喊“城管打人了” https://pbs.twimg.com/amplify_video_thumb/1923271457574141952/img/fdPlfK-RGOk1ZYfp.jpg",
    "images": "",
    "videos": "/tweet/video/whyyoutouzhele/2025/05/16/1923272690200178773_0.jpg,",
    "isReply": false,
    "isRetweet": false,
    "isSelfThread": false,
    "likes": 602,
    "replies": 178,
    "retweets": 75,
    "views": 130374,
    "originVideos": "https://video.twimg.com/amplify_video/1923271457574141952/vid/avc1/540x304/flFLg932OQHs0jQ5.mp4?tag=21,"
  },
  {
    "id": "1923285134859526221",
    "name": "李老师不是你老师",
    "accountId": "whyyoutouzhele",
    "sensitive": false,
    "createdDate": "2025-05-16 15:51:23",
    "content": "5月15日，广东。一群农民工在楼顶跳楼讨薪，其中一名工人站在楼顶边缘大喊：“做工拿不到钱呐！我们打工这么辛苦，我没办法了，我一家老小要吃饭，你们说我该怎么办啊” https://pbs.twimg.com/amplify_video_thumb/1923285024000049152/img/iMWRxyJjiOKhj0fo.jpg",
    "images": "",
    "videos": "/tweet/video/whyyoutouzhele/2025/05/16/1923285134859526221_0.jpg,",
    "isReply": false,
    "isRetweet": false,
    "isSelfThread": false,
    "likes": 550,
    "replies": 74,
    "retweets": 53,
    "views": 110887,
    "originVideos": "https://video.twimg.com/amplify_video/1923285024000049152/vid/avc1/480x854/YKz4hIqy85JGRf0n.mp4?tag=21,"
  },
  {
    "id": "1923299287674290532",
    "name": "李老师不是你老师",
    "accountId": "whyyoutouzhele",
    "sensitive": false,
    "createdDate": "2025-05-16 16:47:38",
    "content": "海外网：“美国一份最新报告显示，大多数美国家庭收入不足以支撑基本生活费用”引发网民嘲讽。 https://pbs.twimg.com/media/GrDuUsPaEAAxzYH.jpg",
    "images": "/tweet/image/whyyoutouzhele/2025/05/16/1923299287674290532_0.jpg,/tweet/image/whyyoutouzhele/2025/05/16/1923299287674290532_1.jpg,/tweet/image/whyyoutouzhele/2025/05/16/1923299287674290532_2.jpg,",
    "videos": "",
    "isReply": false,
    "isRetweet": false,
    "isSelfThread": false,
    "likes": 599,
    "replies": 55,
    "retweets": 36,
    "views": 128717,
    "originVideos": ""
  },
  {
    "id": "1923305812149076325",
    "name": "李老师不是你老师",
    "accountId": "whyyoutouzhele",
    "sensitive": false,
    "createdDate": "2025-05-16 17:13:33",
    "content": "5月16日上午，四川内江发生一起因停车纠纷引发的命案，致一名男子被捅身亡。当地人称“男子将车停在理发店门口，理发店老板请他不要停在这里，对方不听，于是拔刀杀了再说”\n 警方通报：系停车纠纷，嫌疑人用水果刀将被害人刺伤，经抢救无效死亡，案件正在侦办中。 https://pbs.twimg.com/amplify_video_thumb/1923304736629100544/img/Bvj64U-9Hhtq_YIG.jpg",
    "images": "/tweet/image/whyyoutouzhele/2025/05/16/1923305812149076325_0.jpg,/tweet/image/whyyoutouzhele/2025/05/16/1923305812149076325_1.jpg,",
    "videos": "/tweet/video/whyyoutouzhele/2025/05/16/1923305812149076325_0.jpg,/tweet/video/whyyoutouzhele/2025/05/16/1923305812149076325_1.jpg,",
    "isReply": false,
    "isRetweet": false,
    "isSelfThread": false,
    "likes": 982,
    "replies": 210,
    "retweets": 117,
    "views": 266122,
    "originVideos": "https://video.twimg.com/amplify_video/1923304736629100544/vid/avc1/544x960/Nb7lCcFThyhQDtx5.mp4?tag=21,https://video.twimg.com/amplify_video/1923304750461927424/vid/avc1/544x960/fJTsTM0SxWWnj6v7.mp4?tag=21,"
  },
  {
    "id": "1923316622338715799",
    "name": "李老师不是你老师",
    "accountId": "whyyoutouzhele",
    "sensitive": false,
    "createdDate": "2025-05-16 17:56:30",
    "content": "【新冠又来袭？多地阳性率明显上升】中国疾控中心于5月8日发布的2025年4月全国急性呼吸道传染病哨点监测情况，在3月31日至5月4日的监测期内，门急诊流感样病例中的新冠阳性率出现了明显的增长，从7.5%一路飙升至16.2%，增幅超过一倍；住院严重急性呼吸道感染病例中的新冠阳性率同样不容小觑，由3.3%提 https://pbs.twimg.com/media/GrD98vGa0AAqj4J.jpg",
    "images": "/tweet/image/whyyoutouzhele/2025/05/16/1923316622338715799_0.jpg,/tweet/image/whyyoutouzhele/2025/05/16/1923316622338715799_1.jpg,/tweet/image/whyyoutouzhele/2025/05/16/1923316622338715799_2.jpg,",
    "videos": "/tweet/video/whyyoutouzhele/2025/05/16/1923316622338715799_0.jpg,",
    "isReply": false,
    "isRetweet": false,
    "isSelfThread": false,
    "likes": 452,
    "replies": 119,
    "retweets": 47,
    "views": 154393,
    "originVideos": "https://video.twimg.com/amplify_video/1923316286681190400/vid/avc1/336x720/zorbt--aAfJf42V4.mp4?tag=21,"
  },
  {
    "id": "1923327004444615057",
    "name": "李老师不是你老师",
    "accountId": "whyyoutouzhele",
    "sensitive": false,
    "createdDate": "2025-05-16 18:37:46",
    "content": "近日官方通报河南信阳10名干部违规吃喝，其中一名干部饮酒后死亡，当地县领导明知不报。5月15日，河南全省开展违规吃喝专项整治活动。在河南开封市的一个“党员联谊群”里，有领导在群内通知：“请各村干部，党员高度重视，工作日中午晚上禁止违规吃喝，一经发现严肃处理，希望....班子成员不要往枪口上撞 https://pbs.twimg.com/amplify_video_thumb/1923325830077534208/img/1OOgO940NThs8Auy.jpg",
    "images": "/tweet/image/whyyoutouzhele/2025/05/16/1923327004444615057_0.jpg,/tweet/image/whyyoutouzhele/2025/05/16/1923327004444615057_1.jpg,",
    "videos": "/tweet/video/whyyoutouzhele/2025/05/16/1923327004444615057_0.jpg,/tweet/video/whyyoutouzhele/2025/05/16/1923327004444615057_1.jpg,",
    "isReply": false,
    "isRetweet": false,
    "isSelfThread": false,
    "likes": 233,
    "replies": 38,
    "retweets": 20,
    "views": 92515,
    "originVideos": "https://video.twimg.com/amplify_video/1923325830077534208/vid/avc1/480x854/J8qX-vj1ef83pxEp.mp4?tag=21,https://video.twimg.com/amplify_video/1923325873878671360/vid/avc1/1080x1920/EIXHFpMsIOXexB9n.mp4?tag=21,"
  },
  {
    "id": "1923327744328311005",
    "name": "李老师不是你老师",
    "accountId": "whyyoutouzhele",
    "sensitive": false,
    "createdDate": "2025-05-16 18:40:42",
    "content": "https://x.com/whyyoutouzhele/status/1922356984088502664",
    "images": "",
    "videos": "",
    "isReply": true,
    "isRetweet": false,
    "isSelfThread": false,
    "likes": 115,
    "replies": 6,
    "retweets": 4,
    "views": 107205,
    "originVideos": ""
  },
  {
    "id": "1923332948457034225",
    "name": "李老师不是你老师",
    "accountId": "whyyoutouzhele",
    "sensitive": false,
    "createdDate": "2025-05-16 19:01:23",
    "content": "清华大学人文学院历史系（思想文化研究所）教授彭林：当年我毕业后拒绝穿学位服拍照，因为学位服是西方的，是从基督教的道袍转变过来的。“我在中国毕业，我是中国培养的，我到现在只穿唐装”\n 有大V博主反驳：“可博士和教授职位也是西方传过来的，他为啥不拒绝？” https://pbs.twimg.com/amplify_video_thumb/1923332690234994688/img/miJxSPAJ58g-3xE8.jpg",
    "images": "/tweet/image/whyyoutouzhele/2025/05/16/1923332948457034225_0.jpg,/tweet/image/whyyoutouzhele/2025/05/16/1923332948457034225_1.jpg,",
    "videos": "/tweet/video/whyyoutouzhele/2025/05/16/1923332948457034225_0.jpg,",
    "isReply": false,
    "isRetweet": false,
    "isSelfThread": false,
    "likes": 633,
    "replies": 103,
    "retweets": 55,
    "views": 113826,
    "originVideos": "https://video.twimg.com/amplify_video/1923332690234994688/vid/avc1/720x1280/QZDiOoTbVNNRMUJM.mp4?tag=21,"
  },
  {
    "id": "1923337017238446094",
    "name": "李老师不是你老师",
    "accountId": "whyyoutouzhele",
    "sensitive": false,
    "createdDate": "2025-05-16 19:17:33",
    "content": "最近一段时间，欧盟与北京的关系出现了一些缓和的迹象。4月底，中国决定解除自2021年起对五名欧洲议会议员所实施的制裁。引发外界猜测北京方面希望重启中欧投资协定谈判。不过欧盟驻华代表团贸易与投资处处长汉诺宁近日在北京发表讲话时表示，欧方目前无意重启有关《欧中投资协定》（CAI）的谈判，「目 https://pbs.twimg.com/media/GrEQl8QbkAAZuw6.jpg",
    "images": "/tweet/image/whyyoutouzhele/2025/05/16/1923337017238446094_0.jpg,/tweet/image/whyyoutouzhele/2025/05/16/1923337017238446094_1.jpg,",
    "videos": "",
    "isReply": false,
    "isRetweet": false,
    "isSelfThread": false,
    "likes": 233,
    "replies": 28,
    "retweets": 16,
    "views": 89147,
    "originVideos": ""
  },
  {
    "id": "1923340395989127344",
    "name": "李老师不是你老师",
    "accountId": "whyyoutouzhele",
    "sensitive": false,
    "createdDate": "2025-05-16 19:30:58",
    "content": "国家统计局今天公布的数据显示，去年全国城镇非私营单位就业人员年平均工资124110元，比上年增加3412元。\n 去年全国城镇私营单位就业人员年平均工资69476元，比上年增加1136元。 https://t.co/FE8E8aR1Wn",
    "images": "/tweet/image/whyyoutouzhele/2025/05/16/1923340395989127344_0.jpg,",
    "videos": "",
    "isReply": false,
    "isRetweet": false,
    "isSelfThread": false,
    "likes": 10,
    "replies": 6,
    "retweets": 1,
    "views": 3234,
    "originVideos": ""
  },
  {
    "id": "1923349694949757118",
    "name": "李老师不是你老师",
    "accountId": "whyyoutouzhele",
    "sensitive": false,
    "createdDate": "2025-05-16 20:07:56",
    "content": "多位博主呼吁卫建委等有关部门，彻查协和4+4项目里的所有学生。博主称“我拒绝相信协和4+4项目招收的200多名学生里，只有董袭莹一人的资料是伪造的”\n “当你看到一只蟑螂，证明至少有一千只，当我们看到一个董小姐呢？”\nhttps://t.co/DOqqmdlOjY https://t.co/juCzAhZZKv",
    "images": "/tweet/image/whyyoutouzhele/2025/05/16/1923349694949757118_0.jpg,/tweet/image/whyyoutouzhele/2025/05/16/1923349694949757118_1.jpg,/tweet/image/whyyoutouzhele/2025/05/16/1923349694949757118_2.jpg,/tweet/image/whyyoutouzhele/2025/05/16/1923349694949757118_3.jpg,",
    "videos": "",
    "isReply": false,
    "isRetweet": false,
    "isSelfThread": false,
    "likes": 3,
    "replies": 0,
    "retweets": 0,
    "views": 481,
    "originVideos": ""
  },
  {
    "id": "1923350357972824253",
    "name": "李老师不是你老师",
    "accountId": "whyyoutouzhele",
    "sensitive": false,
    "createdDate": "2025-05-16 20:10:34",
    "content": "多位博主呼吁卫建委等有关部门，彻查协和4+4项目里的所有学生。博主称“我拒绝相信协和4+4项目招收的200多名学生里，只有董袭莹一人的资料是伪造的”  “当你看到一只蟑螂，证明至少有一千只，当我们看到一个董小姐呢？” https://pbs.twimg.com/media/GrEc4snaAAAWPvY.jpg",
    "images": "/tweet/image/whyyoutouzhele/2025/05/16/1923350357972824253_0.jpg,/tweet/image/whyyoutouzhele/2025/05/16/1923350357972824253_1.jpg,/tweet/image/whyyoutouzhele/2025/05/16/1923350357972824253_2.jpg,/tweet/image/whyyoutouzhele/2025/05/16/1923350357972824253_3.jpg,",
    "videos": "",
    "isReply": true,
    "isRetweet": false,
    "isSelfThread": false,
    "likes": 323,
    "replies": 22,
    "retweets": 16,
    "views": 77150,
    "originVideos": ""
  },
  {
    "id": "1923353764041572438",
    "name": "李老师不是你老师",
    "accountId": "whyyoutouzhele",
    "sensitive": false,
    "createdDate": "2025-05-16 20:24:06",
    "content": "国家卫建委：协和董袭莹入学资格造假、还存在抄袭剽窃等学术不端行为，撤销董袭莹四项证书。媒体人项栋梁对此提出质疑：协和医学院只需要向学校发一封邮件，便能核实董袭莹报名时提交的学历、学位证书，还有成绩单。那么伪造学历成绩信息的董袭莹，入学协和医学院时是怎么通过资料审查的？是谁放过她的 https://pbs.twimg.com/media/GrEfuyQagAA-_NB.jpg",
    "images": "/tweet/image/whyyoutouzhele/2025/05/16/1923353764041572438_0.jpg,/tweet/image/whyyoutouzhele/2025/05/16/1923353764041572438_1.jpg,/tweet/image/whyyoutouzhele/2025/05/16/1923353764041572438_2.jpg,",
    "videos": "",
    "isReply": false,
    "isRetweet": false,
    "isSelfThread": false,
    "likes": 704,
    "replies": 79,
    "retweets": 68,
    "views": 137755,
    "originVideos": ""
  },
  {
    "id": "1923356731138023725",
    "name": "李老师不是你老师",
    "accountId": "whyyoutouzhele",
    "sensitive": false,
    "createdDate": "2025-05-16 20:35:53",
    "content": "国家统计局今天公布的数据显示，去年全国城镇非私营单位就业人员年平均工资124110元，比上年增加3412元。\n 去年全国城镇私营单位就业人员年平均工资69476元，比上年增加1136元。 https://pbs.twimg.com/media/GrEinhrawAAqX4S.jpg",
    "images": "/tweet/image/whyyoutouzhele/2025/05/16/1923356731138023725_0.jpg,/tweet/image/whyyoutouzhele/2025/05/16/1923356731138023725_1.jpg,/tweet/image/whyyoutouzhele/2025/05/16/1923356731138023725_2.jpg,",
    "videos": "",
    "isReply": false,
    "isRetweet": false,
    "isSelfThread": false,
    "likes": 396,
    "replies": 86,
    "retweets": 30,
    "views": 144907,
    "originVideos": ""
  },
  {
    "id": "1923362743798661164",
    "name": "李老师不是你老师",
    "accountId": "whyyoutouzhele",
    "sensitive": false,
    "createdDate": "2025-05-16 20:59:47",
    "content": "土耳其外交部表示，俄乌谈判已经结束。据媒体报道，俄罗斯代表团在会谈中提出要求控制乌克兰五个地区，并放弃加入北约并成为中立国家。乌克兰拒绝了这些条款，认为这相当于投降，并寻求美国及北约等盟友提供未来安全保障。 https://t.co/uSfxf1avDv",
    "images": "/tweet/image/whyyoutouzhele/2025/05/16/1923362743798661164_0.jpg,",
    "videos": "",
    "isReply": false,
    "isRetweet": false,
    "isSelfThread": false,
    "likes": 0,
    "replies": 0,
    "retweets": 0,
    "views": 5,
    "originVideos": ""
  },
  {
    "id": "1923363528800428209",
    "name": "李老师不是你老师",
    "accountId": "whyyoutouzhele",
    "sensitive": false,
    "createdDate": "2025-05-16 21:02:54",
    "content": "俄乌谈判已经结束。据报道，俄罗斯代表团在会谈中提出要求控制乌克兰五个地区，放弃加入北约并成为中立国家。乌克兰拒绝了这些条款，认为这相当于投降，并寻求美国及北约等盟友提供未来安全保障。 https://pbs.twimg.com/media/GrEnz1BaMAAORZI.png",
    "images": "/tweet/image/whyyoutouzhele/2025/05/16/1923363528800428209_0.jpg,",
    "videos": "",
    "isReply": false,
    "isRetweet": false,
    "isSelfThread": false,
    "likes": 626,
    "replies": 86,
    "retweets": 45,
    "views": 147018,
    "originVideos": ""
  },
  {
    "id": "1923368843356823630",
    "name": "李老师不是你老师",
    "accountId": "whyyoutouzhele",
    "sensitive": false,
    "createdDate": "2025-05-16 21:24:01",
    "content": "5月16日，四川成都。王女士称，56岁的父亲在成都达利园食品厂上班，每天工作十几个小时，最终被活活累死，而工厂拒不处理也不赔偿。他们去工厂讨说法却被保安拦在门外不让进入。 https://pbs.twimg.com/amplify_video_thumb/1923368619817553920/img/X9Rt2D5a80NLD0h1.jpg",
    "images": "",
    "videos": "/tweet/video/whyyoutouzhele/2025/05/16/1923368843356823630_0.jpg,",
    "isReply": false,
    "isRetweet": false,
    "isSelfThread": false,
    "likes": 623,
    "replies": 74,
    "retweets": 98,
    "views": 110514,
    "originVideos": "https://video.twimg.com/amplify_video/1923368619817553920/vid/avc1/480x854/ZWjeOmav48LgbCNg.mp4?tag=21,"
  },
  {
    "id": "1923373955122860538",
    "name": "李老师不是你老师",
    "accountId": "whyyoutouzhele",
    "sensitive": false,
    "createdDate": "2025-05-16 21:44:20",
    "content": "5月16日消息，广西壮族自治区党委副书记蓝天立，因涉嫌严重违纪违法被查。中国官媒“政知见”报道称：这再次警示我们，没有免罪“丹书铁券”，也没有“铁帽子王”，任何人无论是谁，无论位置多特殊、身份多特殊，只要触犯了党纪国法，都将受到严肃惩处。 https://pbs.twimg.com/media/GrEyaX5bwAAC_c6.jpg",
    "images": "/tweet/image/whyyoutouzhele/2025/05/16/1923373955122860538_0.jpg,/tweet/image/whyyoutouzhele/2025/05/16/1923373955122860538_1.jpg,",
    "videos": "",
    "isReply": false,
    "isRetweet": false,
    "isSelfThread": false,
    "likes": 549,
    "replies": 94,
    "retweets": 28,
    "views": 499314,
    "originVideos": ""
  },
  {
    "id": "1923379655190704557",
    "name": "李老师不是你老师",
    "accountId": "whyyoutouzhele",
    "sensitive": false,
    "createdDate": "2025-05-16 22:06:59",
    "content": "美国民主党联邦众议员克利什纳穆希15日呼吁，将雷根政府时期的「对台六项保证法案」正式纳入美国法律。「对台六项保证法案」包括：美国不会设定停止对台军售的日期、美国不会修改「台湾关系法」的相关规定、美国不会在决定对台军售前和中国咨商、美国不会在台湾与中国间担任调人；关于台湾主权，美国不 https://t.co/jewPuj090l",
    "images": "/tweet/image/whyyoutouzhele/2025/05/16/1923379655190704557_0.jpg,",
    "videos": "/tweet/video/whyyoutouzhele/2025/05/16/1923379655190704557_0.jpg,",
    "isReply": false,
    "isRetweet": false,
    "isSelfThread": false,
    "likes": 345,
    "replies": 35,
    "retweets": 36,
    "views": 102704,
    "originVideos": "https://video.twimg.com/amplify_video/1923379445374832641/vid/avc1/640x360/CkiMrYqbSqTlESxo.mp4?tag=21,"
  },
  {
    "id": "1923400492652380471",
    "name": "李老师不是你老师",
    "accountId": "whyyoutouzhele",
    "sensitive": false,
    "createdDate": "2025-05-16 23:29:47",
    "content": "日媒报道，一辆挂着川口市车牌的SUV车辆14日下午在埼玉县三乡市中央地区突然暴冲撞上10名正结伴放学回家的小学生，导致4名就读于小学六年级的男童受伤，4人分别受到轻重伤。\n 肇事车辆犯案后随即加速逃逸，警方15日在距离事故现场约2公里外的一处公寓停车场内寻获该辆车并予以扣押。警方追查发现，车辆的登记车主是一名中国籍男子，而事发当时他就坐在副驾驶座，因此传唤其到案说明。经过调查，肇事男子确定也是中国籍，但目前仍在逃，警方无法与其取得联系。由于副驾男子可能熟知驾驶身份与案发当下情况，因此警方已展开深入讯问，希望掌握更多线索。",
    "images": "",
    "videos": "/tweet/video/whyyoutouzhele/2025/05/16/1923400492652380471_0.jpg,/tweet/video/whyyoutouzhele/2025/05/16/1923400492652380471_1.jpg,",
    "isReply": false,
    "isRetweet": false,
    "isSelfThread": false,
    "likes": 0,
    "replies": 0,
    "retweets": 0,
    "views": 17,
    "originVideos": "https://video.twimg.com/amplify_video/1923399890794881024/vid/avc1/480x270/q5gIZmHehDJ2dTsO.mp4,https://video.twimg.com/amplify_video/1923400187026055168/vid/avc1/480x270/nIatdKCBp7Cb6WvI.mp4"
  },
  {
    "id": "1923401009155690738",
    "name": "李老师不是你老师",
    "accountId": "whyyoutouzhele",
    "sensitive": false,
    "createdDate": "2025-05-16 23:31:50",
    "content": "一辆SUV车辆14日下午在日本埼玉县三乡市中央地区突然暴冲撞上10名正结伴放学回家的小学生，导致4名六年级的男童受伤，肇事车辆犯案后随即加速逃逸，警方15日在距离事故现场约2公里外的一处公寓停车场内寻获该辆车并予以扣押。警方追查发现，车辆的登记车主是一名中国籍男子，而事发当时他就坐在副驾驶 https://t.co/KMMFmOlk33",
    "images": "",
    "videos": "/tweet/video/whyyoutouzhele/2025/05/16/1923401009155690738_0.jpg,/tweet/video/whyyoutouzhele/2025/05/16/1923401009155690738_1.jpg,",
    "isReply": false,
    "isRetweet": false,
    "isSelfThread": false,
    "likes": 1407,
    "replies": 198,
    "retweets": 227,
    "views": 280495,
    "originVideos": "https://video.twimg.com/amplify_video/1923399890794881024/vid/avc1/1280x720/UFcAEdvdO8Q1Da98.mp4?tag=21,https://video.twimg.com/amplify_video/1923400187026055168/vid/avc1/640x360/Tu6l1XuZ3CA0zoXg.mp4?tag=21,"
  },
  {
    "id": "1923407544657002839",
    "name": "李老师不是你老师",
    "accountId": "whyyoutouzhele",
    "sensitive": false,
    "createdDate": "2025-05-16 23:57:48",
    "content": "5月15日(发布) 雷军在最新的内部演讲中说：三月底，一场突如其来的交通事故把这一切都击碎了。我们受到了狂风暴雨般的质疑、批评和指责，我和同事们一样，一下子都懵了。谁也没有想到，这一场事故的影响如此之大，对我们小米的打击也如此之大…… https://t.co/CXqs6YANwm",
    "images": "/tweet/image/whyyoutouzhele/2025/05/16/1923407544657002839_0.jpg,",
    "videos": "/tweet/video/whyyoutouzhele/2025/05/16/1923407544657002839_0.jpg,",
    "isReply": false,
    "isRetweet": false,
    "isSelfThread": false,
    "likes": 6,
    "replies": 3,
    "retweets": 0,
    "views": 825,
    "originVideos": "https://video.twimg.com/amplify_video/1923407368467148800/vid/avc1/320x568/Z_RIBD46YZ4S5iO-.mp4"
  }
]